<?xml version="1.0" encoding="UTF-8"?>
<!DOCTYPE tiles-definitions PUBLIC  
       "-//Apache Software Foundation//DTD Tiles Configuration 3.0//EN"  
       "http://tiles.apache.org/dtds/tiles-config_3_0.dtd">  
<tiles-definitions>  
    <!-- Base Define -->
   
    
    
    <definition name="base.definition" 
        template="/WEB-INF/pages/layouts/layout.jsp">  
        <put-attribute name="title" value="" />  
        <put-attribute name="header" value="/WEB-INF/pages/head.jsp" />  
        <put-attribute name="head" value="/WEB-INF/pages/header.jsp"></put-attribute>
        <put-attribute name="menu" value="/WEB-INF/pages/navbar.jsp" />  
        <put-attribute name="body" value="" />  
    </definition>  
 
    <!-- Home Page -->
    <definition name="home" extends="base.definition">  
        <put-attribute name="title" value="Home Page" />  
        <put-attribute name="body" value="/WEB-INF/pages/home.jsp" />  
    </definition>  
       
    <!-- ContactUs Page -->
    <definition name="users" extends="base.definition">  
        <put-attribute name="title" value="Users" />  
        <put-attribute name="body" value="/WEB-INF/pages/client/manage/user/users.jsp" />  
    </definition>  
    
    <definition name="orgdefinition" extends="base.definition">  
        <put-attribute name="title" value="Company Details" />  
        <put-attribute name="body" value="/WEB-INF/pages/organization/orgdefinition.jsp" />  
    </definition>  
    
    <definition name="currency" extends="base.definition">  
        <put-attribute name="title" value="Currency Definition" />  
        <put-attribute name="body" value="/WEB-INF/pages/setups/currencies.jsp" />  
    </definition> 
    
     <definition name="ratetypes" extends="base.definition">  
        <put-attribute name="title" value="Rate Type Definition" />  
        <put-attribute name="body" value="/WEB-INF/pages/setups/ratetypes.jsp" />  
    </definition> 
    
    <definition name="rentalstruct" extends="base.definition">  
        <put-attribute name="title" value="Rental Structures" />  
        <put-attribute name="body" value="/WEB-INF/pages/setups/rentalstructures.jsp" />  
    </definition> 
    
      <definition name="tenantList" extends="base.definition">  
        <put-attribute name="title" value="Landlord Details" />  
        <put-attribute name="body" value="/WEB-INF/pages/setups/tenantdef.jsp" />  
    </definition> 


      <definition name="paymodesList" extends="base.definition">  
        <put-attribute name="title" value="Payment Modes List" />  
        <put-attribute name="body" value="/WEB-INF/pages/setups/paymentmodes.jsp" />  
    </definition>
    
     <definition name="tenantform" extends="base.definition">  
        <put-attribute name="title" value="Landlord Details" />  
        <put-attribute name="body" value="/WEB-INF/pages/setups/tenantform.jsp" />  
    </definition> 
    
     <definition name="rentalform" extends="base.definition">  
        <put-attribute name="title" value="Enter Rental Structure Details" />  
        <put-attribute name="body" value="/WEB-INF/pages/setups/rentalstructform.jsp" />  
    </definition> 
    
    <definition name="unittypes" extends="base.definition">  
        <put-attribute name="title" value="Unit Type Definition" />  
        <put-attribute name="body" value="/WEB-INF/pages/setups/unittype.jsp" />  
    </definition> 
    
    <definition name="countries" extends="base.definition">  
        <put-attribute name="title" value="Countries/Counties/Towns Definition" />  
        <put-attribute name="body" value="/WEB-INF/pages/setups/countries.jsp" />  
    </definition> 
    
     <definition name="orgSetupScreen" extends="base.definition">  
        <put-attribute name="title" value="Company Set Up" />  
        <put-attribute name="body" value="/WEB-INF/pages/submenus/orgSetupScreen.jsp" />  
    </definition>  
    
     <definition name="uwsetups" extends="base.definition">  
        <put-attribute name="title" value="Underwriting Parameters" />  
        <put-attribute name="body" value="/WEB-INF/pages/submenus/setupScreen.jsp" />  
    </definition>  
    
     <definition name="productsdefinition" extends="base.definition">  
        <put-attribute name="title" value="Products" />  
        <put-attribute name="body" value="/WEB-INF/pages/products/products.jsp" />  
    </definition>  
    
    <definition name="entities" extends="base.definition">  
        <put-attribute name="title" value="Entities Search" />  
        <put-attribute name="body" value="/WEB-INF/pages/entities/entities.jsp" />  
    </definition>  
    
     <definition name="createentity" extends="base.definition">  
        <put-attribute name="title" value="Entities Details" />  
        <put-attribute name="body" value="/WEB-INF/pages/entities/entityform.jsp" />  
    </definition>  
    
</tiles-definitions> 